otp_u2f/__init__.py
otp_u2f/admin.py
otp_u2f/apps.py
otp_u2f/forms.py
otp_u2f/models.py
otp_u2f/urls.py
otp_u2f/utils.py
otp_u2f/views.py
otp_u2f/migrations/0001_initial.py
otp_u2f/migrations/0002_webauthn.py
otp_u2f/migrations/__init__.py
otp_u2f/static/js/base64url-arraybuffer.js
otp_u2f/static/js/cbor.js
otp_u2f/templates/kleides_mfa/device_u2f_create_form.html
otp_u2f/templates/kleides_mfa/device_u2f_verify_form.html
django_otp_u2f-0.3.3.dist-info/AUTHORS.rst
django_otp_u2f-0.3.3.dist-info/LICENSE
django_otp_u2f-0.3.3.dist-info/METADATA
django_otp_u2f-0.3.3.dist-info/WHEEL
django_otp_u2f-0.3.3.dist-info/top_level.txt
django_otp_u2f-0.3.3.dist-info/RECORD
