Metadata-Version: 2.1
Name: django-otp-u2f
Version: 0.3.3
Summary: django-otp device implementation for U2F/Webauthn
Home-page: https://github.com/ossobv/django-otp-u2f/
Author: Harm Geerts
Author-email: hgeerts@osso.nl
License: GNU General Public License v3
Keywords: django-otp universal 2nd factor u2f yubico webauthn
Classifier: Development Status :: 4 - Beta
Classifier: Intended Audience :: Developers
Classifier: License :: OSI Approved :: GNU General Public License v3 (GPLv3)
Classifier: Environment :: Web Environment
Classifier: Natural Language :: English
Classifier: Framework :: Django
Classifier: Framework :: Django :: 4.2
Classifier: Framework :: Django :: 5.0
Classifier: Programming Language :: Python
Classifier: Programming Language :: Python :: 3
Classifier: Programming Language :: Python :: 3.8
Classifier: Programming Language :: Python :: 3.9
Classifier: Programming Language :: Python :: 3.10
Classifier: Programming Language :: Python :: 3.11
Classifier: Programming Language :: Python :: 3.12
Classifier: Topic :: System :: Systems Administration :: Authentication/Directory
Requires-Python: >=3.8
License-File: LICENSE
License-File: AUTHORS.rst
Requires-Dist: django-otp >=1.5.1
Requires-Dist: fido2 <2.0,>=1.1.3
Provides-Extra: docs
Requires-Dist: readthedocs-sphinx-search ==0.1.0 ; extra == 'docs'
Requires-Dist: Sphinx ==4.0.3 ; extra == 'docs'
Requires-Dist: sphinx-rtd-theme ==0.5.2 ; extra == 'docs'
Provides-Extra: kleides-mfa
Requires-Dist: kleides-mfa >=0.2.2 ; extra == 'kleides-mfa'
Provides-Extra: test
Requires-Dist: coverage ; extra == 'test'
Requires-Dist: factory-boy ; extra == 'test'
Requires-Dist: pytest ; extra == 'test'
Requires-Dist: pytest-cov ; extra == 'test'
Requires-Dist: pytest-django ; extra == 'test'
